jira_helper/__init__.py
jira_helper/settings.ini
jira_helper/scripts/__init__.py
jira_helper/scripts/repl.py
jira_helper-0.0.6.dist-info/LICENSE.txt
jira_helper-0.0.6.dist-info/METADATA
jira_helper-0.0.6.dist-info/WHEEL
jira_helper-0.0.6.dist-info/entry_points.txt
jira_helper-0.0.6.dist-info/top_level.txt
jira_helper-0.0.6.dist-info/RECORD
