Metadata-Version: 2.1
Name: jira-helper
Version: 0.0.6
Summary: CLI tools and REPL for passing JQL to a JIRA server and filtering results
Home-page: https://github.com/kenjyco/jira-helper
Author: Ken
Author-email: kenjyco@gmail.com
License: MIT
Download-URL: https://github.com/kenjyco/jira-helper/tarball/v0.0.6
Keywords: jira,jql,repl,cli,command-line,helper,kenjyco
Platform: UNKNOWN
Classifier: Development Status :: 3 - Alpha
Classifier: Environment :: Console
Classifier: Intended Audience :: Developers
Classifier: License :: OSI Approved :: MIT License
Classifier: Operating System :: MacOS :: MacOS X
Classifier: Operating System :: POSIX :: Linux
Classifier: Programming Language :: Python :: 3.5
Classifier: Programming Language :: Python
Classifier: Topic :: Software Development :: Libraries
Classifier: Topic :: Utilities
Requires-Dist: chloop
Requires-Dist: requests
Requires-Dist: settings-helper
